aliendev_api/config/mongo.py
aliendev_api/main.py
aliendev_api-0.1.9.dist-info/METADATA
aliendev_api-0.1.9.dist-info/WHEEL
aliendev_api-0.1.9.dist-info/entry_points.txt
aliendev_api-0.1.9.dist-info/RECORD
